{
    "Changes": [
        {
            "Action": "EditData",
            "Target": "Data/Objects",
            "Entries": {
                // Honey Mead
                //
                // Create Original Honey Mead Item
                //
                "Projectile01": {
                    "Name": "Projectile01",
                    "DisplayName": null,
                    "Description": null,
                    "Type": null,
                    "Edibility": 0,
                    "IsDrink": false,
                    "Category": -26,
                    "Price": 1,
                    "SpriteIndex": 0,
                    "Texture": "bonghits.cp.WeaponPack/Projectiles",
                },
                "{{ModId}}.Projectile.02": {
                    "Name": "{{ModId}}.Projectile.02",
                    "DisplayName": null,
                    "Description": null,
                    "Type": null,
                    "Edibility": 0,
                    "IsDrink": false,
                    "Category": -26,
                    "Price": 1,
                    "SpriteIndex": 4,
                    "Texture": "bonghits.cp.WeaponPack/Projectiles",
                },
                "{{ModId}}.Projectile.03": {
                    "Name": "{{ModId}}.Projectile.03",
                    "DisplayName": null,
                    "Description": null,
                    "Type": null,
                    "Edibility": 0,
                    "IsDrink": false,
                    "Category": -26,
                    "Price": 1,
                    "SpriteIndex": 10,
                    "Texture": "bonghits.cp.WeaponPack/Projectiles",
                },
                "{{ModId}}.Projectile.04": {
                    "Name": "{{ModId}}.Projectile.04",
                    "DisplayName": null,
                    "Description": null,
                    "Type": null,
                    "Edibility": 0,
                    "IsDrink": false,
                    "Category": -26,
                    "Price": 1,
                    "SpriteIndex": 14,
                    "Texture": "bonghits.cp.WeaponPack/Projectiles",
                },
                "{{ModId}}.Projectile.05": {
                    "Name": "{{ModId}}.Projectile.05",
                    "DisplayName": null,
                    "Description": null,
                    "Type": null,
                    "Edibility": 0,
                    "IsDrink": false,
                    "Category": -26,
                    "Price": 1,
                    "SpriteIndex": 18,
                    "Texture": "bonghits.cp.WeaponPack/Projectiles",
                },
                "{{ModId}}.Projectile.06": {
                    "Name": "{{ModId}}.Projectile.06",
                    "DisplayName": null,
                    "Description": null,
                    "Type": null,
                    "Edibility": 0,
                    "IsDrink": false,
                    "Category": -26,
                    "Price": 1,
                    "SpriteIndex": 30,
                    "Texture": "bonghits.cp.WeaponPack/Projectiles",
                },
                "{{ModId}}.Projectile.07": {
                    "Name": "{{ModId}}.Projectile.07",
                    "DisplayName": null,
                    "Description": null,
                    "Type": null,
                    "Edibility": 0,
                    "IsDrink": false,
                    "Category": -26,
                    "Price": 1,
                    "SpriteIndex": 32,
                    "Texture": "bonghits.cp.WeaponPack/Projectiles",
                },
                "{{ModId}}.Projectile.08": {
                    "Name": "{{ModId}}.Projectile.08",
                    "DisplayName": null,
                    "Description": null,
                    "Type": null,
                    "Edibility": 0,
                    "IsDrink": false,
                    "Category": -26,
                    "Price": 1,
                    "SpriteIndex": 33,
                    "Texture": "bonghits.cp.WeaponPack/Projectiles",
                },
                "Projectile09": {
                    "Name": "Projectile09",
                    "DisplayName": null,
                    "Description": null,
                    "Type": null,
                    "Edibility": 0,
                    "IsDrink": false,
                    "Category": -26,
                    "Price": 1,
                    "SpriteIndex": 0,
                    "Texture": "bonghits.cp.WeaponPack/ProjectileOne",
                }
            }
        }
    ]
}